accumulate_8bit.sv
module accumulate_8bit(input logic [7:0] data_in,
                       input logic subtract,
                       input logic CLK,
                       input logic reset,
                       output logic [7:0] data_out,
                       output logic c_out);
    logic [7:0] data_in_int;
    assign data_in_int = (subtract)?~data_in:data_in;
    always_ff@(posedge CLK) begin
        if(reset) {c_out, data_out} <= 9'b0;
        else {c_out, data_out} <= data_out + data_in_int + subtract;
    end

endmodule

accumulate_8bit_tb.sv
`timescale 1ns/1ps
`include "accumulate_8bit.sv"

module accumulate_8bit_tb;
    logic [7:0] data_in;
    logic subtract;
    logic CLK;
    logic reset;
    logic [7:0] data_out;
    logic c_out;

    logic [9:0] test_vector[0:7]; 
    int i;

    accumulate_8bit dut(data_in, subtract, CLK, reset, data_out, c_out);

    initial begin
        CLK = 1'b0;
        forever #10 CLK = ~CLK;
    end

    initial begin
        $readmemb("testvectors.mem", test_vector);
        $dumpfile("accumulate_8bit_tb.vcd");
        $dumpvars;

        data_in = 8'b0;
        subtract = 1'b0;
        reset = 1'b1;

        @(posedge CLK)
            #1;
            reset = 1'b0;
        
        for(i = 0; i < 6; i = i + 1) begin
            {reset, subtract, data_in} = test_vector[i];
            @(posedge CLK);
            #1;
        end

        $finish;
    end

    initial begin
    $monitor("time=%0t | reset=%b subtract=%b data_in=%b | data_out=%b c_out=%b",
             $time, reset, subtract, data_in, data_out, c_out);
    end

endmodule

accumulate_8bit_tb.vcd
$date
	Fri Mar 13 16:03:53 2026
$end
$version
	Icarus Verilog
$end
$timescale
	1ps
$end
$scope module accumulate_8bit_tb $end
$var wire 8 ! data_out [7:0] $end
$var wire 1 " c_out $end
$var reg 1 # CLK $end
$var reg 8 $ data_in [7:0] $end
$var reg 1 % reset $end
$var reg 1 & subtract $end
$var integer 32 ' i [31:0] $end
$scope module dut $end
$var wire 1 # CLK $end
$var wire 8 ( data_in [7:0] $end
$var wire 1 % reset $end
$var wire 1 & subtract $end
$var wire 8 ) data_in_int [7:0] $end
$var reg 1 " c_out $end
$var reg 8 * data_out [7:0] $end
$upscope $end
$upscope $end
$enddefinitions $end
$comment Show the parameter values. $end
$dumpall
$end
#0
$dumpvars
bx *
b0 )
b0 (
b0 '
0&
1%
b0 $
0#
x"
bx !
$end
#10000
0"
b0 !
b0 *
1#
#11000
1%
#20000
0#
#30000
1#
#31000
b101 )
0%
b101 $
b101 (
b1 '
#40000
0#
#50000
b101 !
b101 *
1#
#51000
b11 )
b11 $
b11 (
b10 '
#60000
0#
#70000
b1000 !
b1000 *
1#
#71000
b11111101 )
1&
b10 $
b10 (
b11 '
#80000
0#
#90000
1"
b110 !
b110 *
1#
#91000
b111 )
0&
b111 $
b111 (
b100 '
#100000
0#
#110000
0"
b1101 !
b1101 *
1#
#111000
b11111110 )
1&
b1 $
b1 (
b101 '
#120000
0#
#130000
1"
b1100 !
b1100 *
1#
#131000
b1111 )
0&
b1111 $
b1111 (
b110 '
#140000
0#
#150000
0"
b11011 !
b11011 *
1#
#151000
b1 )
b1 $
b1 (
b111 '
#160000
0#
#170000
b11100 !
b11100 *
1#
#171000
b1000 '
