shift_accumulate_8bit.sv
module shift_accumulate_8bit(input logic [7:0] data_in,
                             input logic [2:0] shamt,
                             input logic shift_sel,
                             input logic subtract,
                             input logic CLK,
                             input logic reset,
                             output logic [7:0] data_out,
                             output logic c_out);
    logic [7:0] data_in_int;
    logic [7:0] data_in_shifted;
    assign data_in_int = (subtract)?~data_in_shifted:data_in_shifted;
    
    always_comb begin
        case(shift_sel)
            1'b0: data_in_shifted = data_in << shamt;
            1'b1: data_in_shifted = data_in >>> shamt;
        endcase
    end

    always_ff@(posedge CLK) begin
        if(reset) {c_out, data_out} <= 9'b0;
        else {c_out, data_out} <= data_out + data_in_int + subtract;
    end

endmodule

shift_accumulate_8bit_tb.sv
`timescale 1ns/1ps
`include "shift_accumulate_8bit.sv"

module shift_accumulate_8bit_tb;
    logic [7:0] data_in;
    logic [2:0] shamt;
    logic shift_sel;
    logic subtract;
    logic CLK;
    logic reset;
    logic [7:0] data_out;
    logic c_out;
    logic [13:0] test_vector [0:5];
    int i;
    shift_accumulate_8bit dut(data_in, shamt, shift_sel, subtract, CLK, reset, data_out, c_out);

    initial begin
        CLK = 1'b0;
        forever #10 CLK = ~CLK;
    end

    initial begin
        $readmemb("testvectors2.mem", test_vector);
        $dumpfile("shift_accumulate_8bit_tb.vcd");
        $dumpvars;
        data_in = 8'b0;
        subtract = 1'b0;
        reset = 1'b1;

        @(posedge CLK)
            #1;
            reset = 1'b0;
        
        for(i = 0; i < 6; i = i + 1) begin
            {reset, subtract, shift_sel, shamt, data_in} = test_vector[i];
            @(posedge CLK);
            #1;
        end

        $finish;
    end

    initial begin
        $monitor("time = %0t | data_in = %h, shamt = %h, shift_sel = %h, subtract = %h, CLK = %h, reset = %h || data_out = %h, c_out = %h", $time, data_in, shamt, shift_sel, subtract, CLK, reset, data_out, c_out);
    end

endmodule

shift_accumulate_8bit_tb.vcd
$date
	Fri Mar 13 16:22:52 2026
$end
$version
	Icarus Verilog
$end
$timescale
	1ps
$end
$scope module shift_accumulate_8bit_tb $end
$var wire 8 ! data_out [7:0] $end
$var wire 1 " c_out $end
$var reg 1 # CLK $end
$var reg 8 $ data_in [7:0] $end
$var reg 1 % reset $end
$var reg 3 & shamt [2:0] $end
$var reg 1 ' shift_sel $end
$var reg 1 ( subtract $end
$var integer 32 ) i [31:0] $end
$scope module dut $end
$var wire 1 # CLK $end
$var wire 8 * data_in [7:0] $end
$var wire 1 % reset $end
$var wire 3 + shamt [2:0] $end
$var wire 1 ' shift_sel $end
$var wire 1 ( subtract $end
$var wire 8 , data_in_int [7:0] $end
$var reg 1 " c_out $end
$var reg 8 - data_in_shifted [7:0] $end
$var reg 8 . data_out [7:0] $end
$upscope $end
$upscope $end
$enddefinitions $end
$comment Show the parameter values. $end
$dumpall
$end
#0
$dumpvars
bx .
bx -
bx ,
bx +
b0 *
b0 )
0(
x'
bx &
1%
b0 $
0#
x"
bx !
$end
#10000
0"
b0 !
b0 .
1#
#11000
b0 ,
b0 -
0'
b0 &
b0 +
1%
#20000
0#
#30000
1#
#31000
b11111010 ,
b101 -
0%
1(
b101 $
b101 *
b1 )
#40000
0#
#50000
b11111011 !
b11111011 .
1#
#51000
b11100111 ,
b11000 -
b10 &
b10 +
b1000110 $
b1000110 *
b10 )
#60000
0#
#70000
1"
b11100011 !
b11100011 .
1#
#71000
b11 ,
b11 -
0(
1'
b0 &
b0 +
b11 $
b11 *
b11 )
#80000
0#
#90000
0"
b11100110 !
b11100110 .
1#
#91000
b1111111 ,
b10000000 -
1(
0'
b101 &
b101 +
b1001100 $
b1001100 *
b100 )
#100000
0#
#110000
1"
b1100110 !
b1100110 .
1#
#111000
b10000 ,
b10000 -
0(
1'
b11 &
b11 +
b10000010 $
b10000010 *
b101 )
#120000
0#
#130000
0"
b1110110 !
b1110110 .
1#
#131000
b110 )
